MANIFEST.in
README.md
requirements.in
setup.cfg
setup.py
test-requirements.in
geomeppy/__init__.py
geomeppy/builder.py
geomeppy/extractor.py
geomeppy/idf.py
geomeppy/patches.py
geomeppy/recipes.py
geomeppy/utilities.py
geomeppy/view_geometry.py
geomeppy.egg-info/PKG-INFO
geomeppy.egg-info/SOURCES.txt
geomeppy.egg-info/dependency_links.txt
geomeppy.egg-info/requires.txt
geomeppy.egg-info/top_level.txt
geomeppy/geom/__init__.py
geomeppy/geom/clippers.py
geomeppy/geom/core_perim.py
geomeppy/geom/intersect_match.py
geomeppy/geom/polygons.py
geomeppy/geom/segments.py
geomeppy/geom/surfaces.py
geomeppy/geom/transformations.py
geomeppy/geom/vectors.py
geomeppy/io/__init__.py
geomeppy/io/default.mtl
geomeppy/io/obj.py
tests/__init__.py
tests/conftest.py
tests/test_adjacencies.py
tests/test_builder.py
tests/test_extractor.py
tests/test_get_surfaces.py
tests/test_intersect_match.py
tests/test_obj.py
tests/test_polygons.py
tests/test_recipes.py
tests/test_regressions.py
tests/test_segments.py
tests/test_shading_blocks.py
tests/test_transformations.py
tests/test_tutorial.py
tests/test_zoning_core_perim.py