Metadata-Version: 2.1
Name: geomeppy
Version: 0.11.8
Summary: Geometry editing for E+ idf files
Home-page: https://github.com/jamiebull1/geomeppy
Author: Jamie Bull
Author-email: jamie.bull@oco-carbon.com
License: MIT License
Download-URL: https://github.com/jamiebull1/geomeppy/tarball/v0.11.8
Keywords: EnergyPlus,geometry,building performance simulation
Platform: any
Classifier: Programming Language :: Python :: 2
Classifier: Programming Language :: Python :: 3
Classifier: Development Status :: 3 - Alpha
Classifier: Natural Language :: English
Classifier: Environment :: Console
Classifier: Intended Audience :: Science/Research
Classifier: License :: OSI Approved :: MIT License
Classifier: Operating System :: OS Independent
Classifier: Topic :: Scientific/Engineering
Provides-Extra: testing
